LICENCE.txt
MANIFEST.in
README.txt
setup.py
vispa_augeroffline/__init__.py
vispa_augeroffline/controller.py
vispa_augeroffline/extension.py
vispa_augeroffline.egg-info/PKG-INFO
vispa_augeroffline.egg-info/SOURCES.txt
vispa_augeroffline.egg-info/dependency_links.txt
vispa_augeroffline.egg-info/requires.txt
vispa_augeroffline.egg-info/top_level.txt
vispa_augeroffline/remote/__init__.py
vispa_augeroffline/remote/executeOffline.py
vispa_augeroffline/static/css/styles.css
vispa_augeroffline/static/html/modulelist.html
vispa_augeroffline/static/html/save_xml_files_dialog.html
vispa_augeroffline/static/html/submit_job_dialog.html
vispa_augeroffline/static/img/extmenuicon.png
vispa_augeroffline/static/js/augeroffline.js